seaplan/__init__.py
seaplan/bathy_map.py
seaplan/sea_plan.py
seaplan/sea_plot.py
seaplan/sea_print.py
seaplan/shading.py
seaplan/temp.py
seaplan/validate_json.py
seaplan/version.py
seaplan/_examples/.DS_Store
seaplan/_examples/GEODEVA7.out
seaplan/_examples/GEODEVA7.png
seaplan/_examples/GEODEVA7.seaplan.yaml
seaplan/_examples/GPS_TG_liste_stations.csv
seaplan/_examples/GPS_TG_liste_stations.xls
seaplan/_examples/Geodeva_route.xls
seaplan/_examples/Geodeva_route1.xls
seaplan/_examples/GulfMexico.out
seaplan/_examples/GulfMexico.png
seaplan/_examples/GulfMexico.seaplan.yaml
seaplan/_examples/MayOBS.out
seaplan/_examples/MayOBS.png
seaplan/_examples/MayOBS.seaplan.yaml
seaplan/_examples/MayOBS_stations.csv
seaplan/_examples/README.txt
seaplan/_examples/WCC_VAN.grd
seaplan/data/.DS_Store
seaplan/data/seaplan.schema.json
seaplan-0.5.0.dist-info/LICENSE.txt
seaplan-0.5.0.dist-info/METADATA
seaplan-0.5.0.dist-info/WHEEL
seaplan-0.5.0.dist-info/entry_points.txt
seaplan-0.5.0.dist-info/top_level.txt
seaplan-0.5.0.dist-info/RECORD
