Metadata-Version: 2.1
Name: seaplan
Version: 0.5.0
Summary: Sea-going mission planning
Home-page: https://github.com/WayneCrawford/seaplan
Author: Wayne Crawford
Author-email: crawford@ipgp.fr
Keywords: oceanography,marine,OBS
Classifier: Development Status :: 4 - Beta
Classifier: Environment :: Console
Classifier: Intended Audience :: Science/Research
Classifier: Intended Audience :: Developers
Classifier: License :: OSI Approved :: GNU General Public License v3 (GPLv3)
Classifier: Natural Language :: English
Classifier: Operating System :: OS Independent
Classifier: Programming Language :: Python :: 3
Classifier: Programming Language :: Python :: 3.6
Classifier: Topic :: Scientific/Engineering
Classifier: Topic :: Scientific/Engineering :: Physics
Requires-Python: >=3.9
License-File: LICENSE.txt
Requires-Dist: scipy (>=1.6.3)
Requires-Dist: pyproj (>=3.1.0)
Requires-Dist: shapely (>=1.7)
Requires-Dist: pyshp (>=2.1)
Requires-Dist: matplotlib (>=3.4)
Requires-Dist: fiona (>=1.9.6)
Requires-Dist: cartopy (>=0.22)
Requires-Dist: pyyaml (>=3.0)
Requires-Dist: xarray (>=v2022.03.0)
Requires-Dist: jsonschema (>=3.2)
Requires-Dist: docutils (>=0.20)
Requires-Dist: jsonref (>=1.0)
